HISTORY.txt
LICENSE.txt
MANIFEST.in
generate.py
setup.cfg
setup.py
src/correct_pycountry.egg-info/PKG-INFO
src/correct_pycountry.egg-info/SOURCES.txt
src/correct_pycountry.egg-info/dependency_links.txt
src/correct_pycountry.egg-info/not-zip-safe
src/correct_pycountry.egg-info/top_level.txt
src/pycountry/README.txt
src/pycountry/__init__.py
src/pycountry/db.py
src/pycountry/tests.py
src/pycountry/databases/iso15924.xml
src/pycountry/databases/iso3166.xml
src/pycountry/databases/iso3166_2.xml
src/pycountry/databases/iso4217.xml
src/pycountry/databases/iso639.xml
src/pycountry/locales/af/LC_MESSAGES/iso3166.mo
src/pycountry/locales/af/LC_MESSAGES/iso3166.po
src/pycountry/locales/af/LC_MESSAGES/iso639.mo
src/pycountry/locales/af/LC_MESSAGES/iso639.po
src/pycountry/locales/am/LC_MESSAGES/iso3166.mo
src/pycountry/locales/am/LC_MESSAGES/iso3166.po
src/pycountry/locales/am/LC_MESSAGES/iso639.mo
src/pycountry/locales/am/LC_MESSAGES/iso639.po
src/pycountry/locales/ar/LC_MESSAGES/iso15924.mo
src/pycountry/locales/ar/LC_MESSAGES/iso15924.po
src/pycountry/locales/ar/LC_MESSAGES/iso3166.mo
src/pycountry/locales/ar/LC_MESSAGES/iso3166.po
src/pycountry/locales/ar/LC_MESSAGES/iso639.mo
src/pycountry/locales/ar/LC_MESSAGES/iso639.po
src/pycountry/locales/as/LC_MESSAGES/iso3166.mo
src/pycountry/locales/as/LC_MESSAGES/iso3166.po
src/pycountry/locales/as/LC_MESSAGES/iso639.mo
src/pycountry/locales/as/LC_MESSAGES/iso639.po
src/pycountry/locales/ast/LC_MESSAGES/iso3166.mo
src/pycountry/locales/ast/LC_MESSAGES/iso3166.po
src/pycountry/locales/ast/LC_MESSAGES/iso639.mo
src/pycountry/locales/ast/LC_MESSAGES/iso639.po
src/pycountry/locales/az/LC_MESSAGES/iso3166.mo
src/pycountry/locales/az/LC_MESSAGES/iso3166.po
src/pycountry/locales/az/LC_MESSAGES/iso3166_2.mo
src/pycountry/locales/az/LC_MESSAGES/iso3166_2.po
src/pycountry/locales/az/LC_MESSAGES/iso639.mo
src/pycountry/locales/az/LC_MESSAGES/iso639.po
src/pycountry/locales/be/LC_MESSAGES/iso3166.mo
src/pycountry/locales/be/LC_MESSAGES/iso3166.po
src/pycountry/locales/be/LC_MESSAGES/iso639.mo
src/pycountry/locales/be/LC_MESSAGES/iso639.po
src/pycountry/locales/bg/LC_MESSAGES/iso15924.mo
src/pycountry/locales/bg/LC_MESSAGES/iso15924.po
