Metadata-Version: 1.0
Name: correct-pycountry
Version: 0.12.2
Summary: A fork for pycountry, correct the country name of Taiwan
Home-page: http://bitbucket.org/victorlin/correct_pycountry
Author: Victor Lin
Author-email: bornstub@gmail.com
License: LGPL 2.1
Keywords: country subdivision language currency iso 3166 639 4217 15924 3166-2
Platform: UNKNOWN
